TemplateDemo-0.0.0.dist-info/DESCRIPTION.rst
TemplateDemo-0.0.0.dist-info/METADATA
TemplateDemo-0.0.0.dist-info/RECORD
TemplateDemo-0.0.0.dist-info/WHEEL
TemplateDemo-0.0.0.dist-info/entry_points.txt
TemplateDemo-0.0.0.dist-info/metadata.json
TemplateDemo-0.0.0.dist-info/top_level.txt
demo/__init__.py
demo/__main__.py
demo/sample.py
demo/tests/__init__.py
demo/tests/conftest.py
demo/tests/test_demo.py
site/__init__.py
tests/__init__.py
tests/conftest.py
tests/test_all.py
