Metadata-Version: 2.0
Name: TemplateDemo
Version: 0.0.0
Summary: A sample project templated from jacebrowning/template-python.
Home-page: https://github.com/jacebrowning/template-python-demo
Author: Jace Browning
Author-email: jacebrowning@gmail.com
License: MIT
Platform: UNKNOWN
Classifier: Development Status :: 1 - Planning
Classifier: Natural Language :: English
Classifier: Operating System :: OS Independent
Classifier: Programming Language :: Python
Classifier: Programming Language :: Python :: 2
Classifier: Programming Language :: Python :: 2.7
Classifier: Programming Language :: Python :: 3
Classifier: Programming Language :: Python :: 3.3
Classifier: Programming Language :: Python :: 3.4
Classifier: Programming Language :: Python :: 3.5
Requires-Dist: testpackage (==2.26)
